slicerio/__init__.py
slicerio/_version.py
slicerio/data_helper.py
slicerio/segmentation.py
slicerio/server.py
slicerio/tests/__init__.py
slicerio/tests/test_segmentation.py
slicerio-1.1.1.dist-info/LICENSE
slicerio-1.1.1.dist-info/METADATA
slicerio-1.1.1.dist-info/WHEEL
slicerio-1.1.1.dist-info/top_level.txt
slicerio-1.1.1.dist-info/RECORD
