Metadata-Version: 2.1
Name: slicerio
Version: 1.1.1
Summary: Utilities for 3D Slicer
Home-page: https://github.com/lassoan/slicerio
Download-URL: https://github.com/lassoan/slicerio/archive/master.zip
Author: Andras Lasso
Author-email: lasso@queensu.ca
Maintainer: Andras Lasso
Maintainer-email: lasso@queensu.ca
Keywords: 3DSlicer medical imaging segmentation
Classifier: License :: OSI Approved :: MIT License
Classifier: Intended Audience :: Developers
Classifier: Intended Audience :: Healthcare Industry
Classifier: Intended Audience :: Science/Research
Classifier: Development Status :: 4 - Beta
Classifier: Programming Language :: Python :: 3
Classifier: Operating System :: OS Independent
Classifier: Topic :: Scientific/Engineering :: Medical Science Apps.
Classifier: Topic :: System :: Networking
Requires-Python: >=3.6
License-File: LICENSE
Requires-Dist: pynrrd
Requires-Dist: numpy
Requires-Dist: requests
